getmetasat/__init__.py
getmetasat/autenticacion.py
getmetasat/descargamasiva.py
getmetasat/fiel.py
getmetasat/solicitadescarga.py
getmetasat/validacioncfdi.py
getmetasat/verificasolicituddescarga.py
getmetasat-1.0.0.dist-info/LICENSE
getmetasat-1.0.0.dist-info/METADATA
getmetasat-1.0.0.dist-info/WHEEL
getmetasat-1.0.0.dist-info/top_level.txt
getmetasat-1.0.0.dist-info/RECORD
