Metadata-Version: 2.1
Name: getmetasat
Version: 1.0.0
Summary: Python WSDL SAT - [METADATA]
Home-page: https://electroefos.mx
Author: electroefos.mx
Author-email: ed@electroefos.mx
License: UNKNOWN
Platform: UNKNOWN
Classifier: Programming Language :: Python :: 2.7
Classifier: Programming Language :: Python :: 3
Classifier: License :: OSI Approved :: GNU General Public License v3 (GPLv3)
Classifier: Operating System :: OS Independent
Requires-Dist: lxml (>=4.2.5)
Requires-Dist: requests (>=2.21.0)
Requires-Dist: pycryptodome (>=3.7.2)
Requires-Dist: pyOpenSSL (>=18.0.0)
